nanotrack/__init__.py
nanotrack/detector.py
nanotrack/main.py
nanotrack/main1.py
nanotrack/nanotrack.py
nanotrack/setup.py
tests/__init__.py
tests/test-nanotrack.py
tests/test_nanotrack.py
nanotrack-0.2.1.dist-info/LICENSE
nanotrack-0.2.1.dist-info/METADATA
nanotrack-0.2.1.dist-info/WHEEL
nanotrack-0.2.1.dist-info/top_level.txt
nanotrack-0.2.1.dist-info/RECORD
