Metadata-Version: 2.1
Name: nanotrack
Version: 0.2.1
Summary: A lightweight object detection and tracking package 
Home-page: https://github.com/ragultv/NanoTrack
Author: RAGUL T, KARTHICK RAJA E
Author-email: tragulragul@gmail.com, e.karthickraja2004@gmail.com
Maintainer: RAGUL T
Project-URL: Documentation, https://github.com/ragultv/NanoTrack/blob/main/README.md
Project-URL: Source, https://github.com/ragultv/NanoTrack
Project-URL: Bug Tracker, https://github.com/ragultv/NanoTrack/issues
Keywords: object detection tracking kalman-filter lightweight
Classifier: Programming Language :: Python :: 3
Classifier: License :: OSI Approved :: MIT License
Classifier: Operating System :: OS Independent
Classifier: Topic :: Scientific/Engineering :: Artificial Intelligence
Classifier: Topic :: Multimedia :: Video
Requires-Python: >=3.7
License-File: LICENSE
Requires-Dist: numpy>=1.18.0
Requires-Dist: opencv-python>=4.5.0
Requires-Dist: torch>=1.7.0
Requires-Dist: torchvision>=0.8.0
Requires-Dist: scipy>=1.5.0
Provides-Extra: dev
Requires-Dist: pytest>=6.0; extra == "dev"
Requires-Dist: flake8>=3.8; extra == "dev"
